README.rst
setup.py
automock/__about__.py
automock/__init__.py
automock/base.py
automock/utils.py
automock.egg-info/PKG-INFO
automock.egg-info/SOURCES.txt
automock.egg-info/dependency_links.txt
automock.egg-info/requires.txt
automock.egg-info/top_level.txt
automock/conf/__init__.py
automock/conf/defaults.py