Metadata-Version: 1.1
Name: automock
Version: 1.0.3
Summary: Utility to allow some functions to be 'mocked by default' when running tests.
Home-page: https://github.com/depop/python-automock
Author: Depop
Author-email: dev@depop.com
License: Apache 2.0
Platform: UNKNOWN
Classifier: Environment :: Plugins
Classifier: Intended Audience :: Developers
Classifier: License :: OSI Approved :: Apache Software License
Classifier: Operating System :: OS Independent
Classifier: Programming Language :: Python
Classifier: Programming Language :: Python :: 3.6
Classifier: Programming Language :: Python :: 2.7
